README.md
rpt
setup.py
lib/rpt/__init__.py
lib/rpt.egg-info/PKG-INFO
lib/rpt.egg-info/SOURCES.txt
lib/rpt.egg-info/dependency_links.txt
lib/rpt.egg-info/top_level.txt