Metadata-Version: 2.1
Name: rpt
Version: 2.1.0
Summary: # Repetitive command line creation with your editor of choice
Home-page: http://thp.io/2016/rpt/
Download-URL: http://thp.io/2016/rpt/rpt-2.1.0.tar.gz
Author: Thomas Perl
Author-email: m@thp.io
License: Simplified BSD License
